ait_openapi/__init__.py
ait_openapi/authorize.py
ait_openapi/config.py
ait_openapi/exception.py
ait_openapi/log.py
ait_openapi/openapi_contexvar.py
ait_openapi/schema.py
ait_openapi/middleware/__init__.py
ait_openapi/middleware/context_middleware.py
ke_openapi_ait_client-0.0.1.5.dist-info/METADATA
ke_openapi_ait_client-0.0.1.5.dist-info/WHEEL
ke_openapi_ait_client-0.0.1.5.dist-info/top_level.txt
ke_openapi_ait_client-0.0.1.5.dist-info/RECORD
