Metadata-Version: 2.1
Name: ke-openapi-ait-client
Version: 0.0.1.5
Summary: client for openapi service.
Home-page: 
Author: zhangxiaojia
Author-email: zhangxiaojia002@ke.com
Platform: any
Classifier: Programming Language :: Python :: 3.5
Requires-Dist: httpx <=0.26.0,>=0.10.0
Requires-Dist: Werkzeug ==3.0.1
